{
  "file_id": "832e4a660548",
  "pass_number": 1,
  "content": "**Introduction. to be fair, setting Sail on the Digital Voyage**\n\nMoreover, in the rapidly evolving digital landscape of our time, it's crucial to acknowledge the profound impact of technological advancement on our daily interaction with information. for what it's worth, this advancement lays the groundwork for growth, innovation, and collaboration, while simultaneously introducing complex challenges and uncertainties that demand careful consideration. oddly enough, **Balancing the Pros and Cons of Technological Advancement**\n\nFurthermore, it's essential to ponder not only the potential benefits of these tools but also their potential drawbacks. As technology propels us into the future, we must remain vigilant to the ethical implications and long-term societal effects of these developments. **The Intersection of Humanity and Artificial Intelligence**\n\nIn addition, in the examination of the interplay between humans and artificial intelligence, a comprehensive perspective is necessary. This perspective should include efficiency and productivity, as well as ethical considerations. By doing so, we can achieve outcomes that are both sustainable and effective within the broader context of contemporary progress. **Conclusion: Steering Towards a Balanced Technological Future**\n\nBy contrast, in conclusion. as we navigate the digital landscape, it's imperative to maintain a balanced perspective on the role of technology in our lives. Sometimes considering both the benefits and potential downsides, we can secure a sustainable and efficient future within the framework of modern development.\n",
  "timestamp": 1762253063.183116,
  "file_path": "./output/tmpbeh2dvjz_pass1_sim1.txt",
  "metrics": {
    "changePercent": 96.01163273784795,
    "tensionPercent": 96.01163273784795,
    "scannerRisk": 0.0,
    "success": true,
    "localPath": "./output/tmpbeh2dvjz_pass1_sim1.txt",
    "docId": null,
    "originalLength": 801,
    "finalLength": 1606,
    "processingTime": 32936.53395801084
  },
  "metadata": {
    "input_path": "/var/folders/1f/tr5wzfz93kz0z8jnp14m2k5r0000gn/T/tmpbeh2dvjz.txt",
    "entropy_level": "medium",
    "heuristics": {
      "microstructure_control": true,
      "macrostructure_analysis": true,
      "anti_scanner_techniques": true,
      "refiner_control": 2,
      "entropy_management": 2,
      "semantic_tone_tuning": 1,
      "history_analysis": true,
      "annotation_mode": false,
      "humanize_academic": {
        "enabled": true,
        "intensity": "medium"
      },
      "formatting_safeguards": {
        "enabled": true,
        "mode": "strict"
      },
      "keywords": [],
      "strategy_weights": {
        "clarity": 0.5,
        "persuasion": 0.6499999999999999,
        "brevity": 0.4,
        "formality": 0.6000000000000001
      },
      "entropy": {
        "risk_preference": 0.7,
        "repeat_penalty": 0.8999999999999999,
        "phrase_penalty": 0.6000000000000001
      }
    },
    "processing_time": 32936.53395801084
  }
}